smms/__init__.py
smms/smms.py
smms/utils.py
smms_cascades-1.0.3.dist-info/LICENSE
smms_cascades-1.0.3.dist-info/METADATA
smms_cascades-1.0.3.dist-info/WHEEL
smms_cascades-1.0.3.dist-info/entry_points.txt
smms_cascades-1.0.3.dist-info/top_level.txt
smms_cascades-1.0.3.dist-info/RECORD
