Metadata-Version: 2.1
Name: smms-cascades
Version: 1.0.3
Summary: A command line HTTP client to of https://sm.ms
Home-page: https://github.com/cascades-sjtu/smms-cli
Author: cascades
Author-email: cascades@sjtu.edu.cn
License: UNKNOWN
Project-URL: Bug Tracker, https://github.com/cascades-sjtu/smms-cli/issues
Platform: UNKNOWN
Classifier: Programming Language :: Python :: 3
Classifier: License :: OSI Approved :: MIT License
Classifier: Operating System :: OS Independent
Requires-Python: >=3.6
License-File: LICENSE
